boknows/__init__.py
boknows/utils.py
boknows/cli/__init__.py
boknows/cli/app.py
boknows-0.0.1.dist-info/DESCRIPTION.rst
boknows-0.0.1.dist-info/METADATA
boknows-0.0.1.dist-info/RECORD
boknows-0.0.1.dist-info/WHEEL
boknows-0.0.1.dist-info/entry_points.txt
boknows-0.0.1.dist-info/metadata.json
boknows-0.0.1.dist-info/top_level.txt
tests/__init__.py
tests/test_utils.py
