Metadata-Version: 2.0
Name: boknows
Version: 0.0.1
Summary: Get NCAA stats and figures without the hassle of stats.ncaa.org.
Home-page: https://github.com/nbedi/boknows
Author: Neil Bedi
Author-email: neilbedi@gmail.com
License: MIT
Keywords: ncaa sports college basketball
Platform: UNKNOWN
Classifier: Development Status :: 3 - Alpha
Classifier: Topic :: Software Development :: Libraries :: Python Modules
